stopwatch/__init__.py
stopwatch/stopwatch.py
my_stopwatch-1.0.1.dist-info/LICENSE.txt
my_stopwatch-1.0.1.dist-info/METADATA
my_stopwatch-1.0.1.dist-info/WHEEL
my_stopwatch-1.0.1.dist-info/top_level.txt
my_stopwatch-1.0.1.dist-info/RECORD
